src/__init__.py
src/pytest_sorter.py
tests/__init__.py
tests/conftest.py
tests/test_sorter.py
pytest_sorter-0.3.1.dist-info/LICENSE
pytest_sorter-0.3.1.dist-info/METADATA
pytest_sorter-0.3.1.dist-info/WHEEL
pytest_sorter-0.3.1.dist-info/entry_points.txt
pytest_sorter-0.3.1.dist-info/top_level.txt
pytest_sorter-0.3.1.dist-info/RECORD
