Metadata-Version: 2.1
Name: pytest-sorter
Version: 0.3.1
Summary: A simple plugin to first execute tests that historically failed more
Home-page: https://github.com/AndreMicheletti/pytest-sorter
Author: Andre Luiz Micheletti
Author-email: andreluizmtmicheletti@gmail.com
Maintainer: Andre Luiz Micheletti
Maintainer-email: andreluizmtmicheletti@gmail.com
License: MIT
Platform: any
Classifier: Development Status :: 4 - Beta
Classifier: Framework :: Pytest
Classifier: Intended Audience :: Developers
Classifier: Topic :: Software Development :: Testing
Classifier: Programming Language :: Python
Classifier: Programming Language :: Python :: 3
Classifier: Programming Language :: Python :: 3.6
Classifier: Programming Language :: Python :: 3.7
Classifier: Programming Language :: Python :: Implementation :: CPython
Classifier: Programming Language :: Python :: Implementation :: PyPy
Classifier: Operating System :: OS Independent
Classifier: License :: OSI Approved :: MIT License
Requires-Python: >=3.6
Requires-Dist: pytest (>=3.1.1)
